{
  "_comment": "LibraryService.scan_projects_dir() happy path — 3 phim hop le, sap xep moi nhat truoc",
  "projects_dir": "~/projects",
  "films": [
    {
      "session_id": "sess_20260616_1420_k7p2",
      "created_at": "2026-06-16T14:20:00",
      "frame_count": 12,
      "fps_playback": 8,
      "duration_seconds": 1.5,
      "title": "Khung long phieu luu",
      "creator_name": "",
      "status": "completed",
      "exported": true,
      "mp4_path": "~/projects/sess_20260616_1420_k7p2/output.mp4",
      "gif_path": "~/projects/sess_20260616_1420_k7p2/output.gif",
      "qr_path": "~/projects/sess_20260616_1420_k7p2/qr.png",
      "download_url": "https://neo.mv/phim/k7p2",
      "_computed": {
        "display_name": "Khung long phieu luu",
        "display_date": "16/06/2026 · 14:20",
        "resolution": "1280×960",
        "size_mb": 2.4,
        "badge": "shared"
      }
    },
    {
      "session_id": "sess_20260616_1105_r9a1",
      "created_at": "2026-06-16T11:05:00",
      "frame_count": 16,
      "fps_playback": 8,
      "duration_seconds": 2.0,
      "title": "Ten lua len Sao Hoa",
      "creator_name": "",
      "status": "completed",
      "exported": true,
      "mp4_path": "~/projects/sess_20260616_1105_r9a1/output.mp4",
      "gif_path": "~/projects/sess_20260616_1105_r9a1/output.gif",
      "qr_path": null,
      "download_url": null,
      "_computed": {
        "display_name": "Ten lua len Sao Hoa",
        "display_date": "16/06/2026 · 11:05",
        "resolution": "1280×960",
        "size_mb": 3.1,
        "badge": "local"
      }
    },
    {
      "session_id": "sess_20260615_1640_b3c8",
      "created_at": "2026-06-15T16:40:00",
      "frame_count": 26,
      "fps_playback": 8,
      "duration_seconds": 3.25,
      "title": "",
      "creator_name": "",
      "status": "completed",
      "exported": true,
      "mp4_path": "~/projects/sess_20260615_1640_b3c8/output.mp4",
      "gif_path": "~/projects/sess_20260615_1640_b3c8/output.gif",
      "qr_path": "~/projects/sess_20260615_1640_b3c8/qr.png",
      "download_url": "https://neo.mv/phim/b3c8",
      "_computed": {
        "display_name": "Phim 15/06 16:40",
        "display_date": "15/06/2026 · 16:40",
        "resolution": "1280×960",
        "size_mb": 4.8,
        "badge": "shared"
      }
    }
  ]
}
